quiverquant.py
quiverquant-0.2.2.dist-info/LICENSE
quiverquant-0.2.2.dist-info/METADATA
quiverquant-0.2.2.dist-info/WHEEL
quiverquant-0.2.2.dist-info/top_level.txt
quiverquant-0.2.2.dist-info/RECORD
