Metadata-Version: 2.1
Name: quiverquant
Version: 0.2.2
Summary: Quiver Quantitative Alternative Data
Home-page: https://github.com/Quiver-Quantitative/python-api
Author: Chris Kardatzke
Author-email: chris@quiverquant.com
License: UNKNOWN
Platform: UNKNOWN
Classifier: Programming Language :: Python :: 3
Classifier: License :: OSI Approved :: MIT License
Classifier: Operating System :: OS Independent
Requires-Python: >=3.6
